README.md
setup.py
likpyexp/__init__.py
likpyexp/likpyexp.py
likpyexp.egg-info/PKG-INFO
likpyexp.egg-info/SOURCES.txt
likpyexp.egg-info/dependency_links.txt
likpyexp.egg-info/not-zip-safe
likpyexp.egg-info/top_level.txt