Metadata-Version: 2.1
Name: likpyexp
Version: 1.1
Summary: It has input code and output of 20 Python Experiments
Home-page: UNKNOWN
Author: Likhith Reddy
License: UNKNOWN
Platform: UNKNOWN
